PythonMatrixClass/__init__.py
PythonMatrixClass/matrix.py
PythonMatrixClass/setup.py
PythonMatrixClass-0.1.0.dist-info/METADATA
PythonMatrixClass-0.1.0.dist-info/WHEEL
PythonMatrixClass-0.1.0.dist-info/top_level.txt
PythonMatrixClass-0.1.0.dist-info/RECORD
