Metadata-Version: 2.1
Name: PythonMatrixClass
Version: 0.1.0
Summary: PythonMatrixClass module for Python
Home-page: https://github.com/TvoozMagnificent/Matrix
Author: TvoozMagnificent
Author-email: luchang1106@icloud.com
License: MIT
Platform: UNKNOWN
Classifier: License :: OSI Approved :: MIT License
Classifier: Programming Language :: Python :: 3
Classifier: Programming Language :: Python :: 3.7
